ghostguard/__init__.py
ghostguard/cli.py
ghostguard/config.py
ghostguard/core/__init__.py
ghostguard/core/ai.py
ghostguard/core/corrector.py
ghostguard/core/talk.py
ghostguard/core/voice.py
ghostguard/utils/__init__.py
ghostguard/utils/formatter.py
ghostguard-1.6.dist-info/METADATA
ghostguard-1.6.dist-info/WHEEL
ghostguard-1.6.dist-info/entry_points.txt
ghostguard-1.6.dist-info/top_level.txt
ghostguard-1.6.dist-info/RECORD
