Metadata-Version: 2.1
Name: ghostguard
Version: 1.6
Summary: GhostGuard CLI — AI-powered Smart Corrector and Talk Assistant
Author: Souparno Goswami
Classifier: Programming Language :: Python :: 3
Classifier: Operating System :: OS Independent
Classifier: Intended Audience :: Developers
Classifier: Topic :: Utilities
Classifier: Topic :: Software Development :: Libraries
Requires-Python: >=3.8
Requires-Dist: pyfiglet
Requires-Dist: colorama
Requires-Dist: python-dotenv
Requires-Dist: google-genai
Requires-Dist: pyttsx3
Requires-Dist: pyreadline3
